Workbook

Sheet README
B2: MCBOMs Worked Example — Excel Validation
B4: Purpose
B5: This workbook implements the MCBOMs MILP — the same Mixed-Integer Linear Program specified in Chapter 2 of the Methodology document and implemented in Python in the project's optimizer module — using the Solver add-in built into Microsoft Excel. It validates the MILP against the worked example presented in Section 2.3.7 of the Methodology, which provides a hand-calculated reference answer. All five forms of the MCBOMs MILP — Python, AMPL, GAMS, LP, and this Excel implementation — produce numerically identical results. Project website: https://ttitamu.github.io/mcboms-optimization.
B11: Problem
B12: A single 5-mile rural two-lane highway segment is considered for a lane-widening treatment (10 ft → 12 ft, CMF = 0.88). The optimization decides whether to implement the treatment given a $1,000,000 budget. Expected outcome: fund the treatment (its present-value safety benefit exceeds its cost).
B17: Expected result
B18: Quantity | C18: Value
B19: Annual safety benefit | C19: 211810
B20: Present-value safety benefit (PWF × annual) | C20: 2243914
B21: Treatment cost | C21: 750000
B22: Net benefit if treatment funded | C22: 1493914
B23: Optimal Solver objective value | C23: 1493914
B26: How to run
B27: 1. Open this workbook in Microsoft Excel (desktop). The Solver add-in must be enabled — see 'How to enable the Solver add-in' below if Solver does not appear on the Data tab.
B28: 2. Go to the 'Optimization' sheet. Verify that the decision-variable cells (yellow-shaded, 'Fund? (0/1)' column) are currently 0.
B29: 3. On the Data tab, click Solver. The Solver Parameters dialog opens.
B30: 4. Configure Solver per the instructions on the right-side panel of the 'Optimization' sheet (objective cell, decision range, constraints).
B31: 5. Click Solve. When the Solver Results dialog appears, choose 'Keep Solver Solution' and click OK.
B32: 6. Verify the answer matches the 'Expected result' table above. The 'Results' sheet shows the selected alternatives and a match indicator that displays 'Run Solver' (yellow) before Solver has been used, 'PASS' (green) once the optimal answer is reached, or 'FAIL' (red) if the answer does not match.
B34: How to enable the Solver add-in (one-time setup)
B35: Skip this section if the Solver button is already visible on the Data tab.
B36: 1. File → Options → Add-ins.
B37: 2. At the bottom, set Manage to 'Excel Add-ins' and click Go.
B38: 3. Check the 'Solver Add-in' box and click OK.
... B45: Discount rate (7% real, 2023 dollars) — USDOT BCA Guidance May 2025, Section 4.3

Sheet Inputs
B2: Inputs
B3: Cost and benefit values for the worked example. The Calculation sheet shows the derivation of the $2,243,914 present-value safety benefit from the per-severity crash data.
B6: Budget | E6: 1000000
B10: Site | C10: Alt | D10: Description | E10: Resurf cost | F10: Safety cost | G10: Total cost | H10: Safety ben | I10: Ops ben | J10: Total ben | K10: Net benefit
B11: 1 | C11: 0 | D11: Do nothing | E11: 0 | F11: 0 | G11: =E11+F11 | H11: 0 | I11: 0 | J11: =H11+I11 | K11: =J11-G11
B12: 1 | C12: 1 | D12: Lane widening 10ft → 12ft (CMF 0.88) | E12: 0 | F12: 750000 | G12: =E12+F12 | H12: 2243914 | I12: 0 | J12: =H12+I12 | K12: =J12-G12

Sheet Calculation
B2: Calculation: Present-Value Safety Benefit
B3: Reproduces Methodology Section 2.3.7 derivation of the safety benefit. Annual safety benefit × PWF(0.07, 20) = $211,810 × 10.594 = $2,243,914.
B6: Per-severity calculation
B7: Severity | C7: Share | D7: E_no-build | E7: E_build (× CMF) | F7: Reduction | G7: Unit cost | H7: Annual benefit
B8: K | C8: 0.013 | D8: 0.078 | E8: =D8*0.88 | F8: =D8-E8 | G8: 13200000 | H8: =F8*G8
B9: A | C9: 0.065 | D9: 0.39 | E9: =D9*0.88 | F9: =D9-E9 | G9: 1254700 | H9: =F9*G9
B10: B | C10: 0.095 | D10: 0.57 | E10: =D10*0.88 | F10: =D10-E10 | G10: 246900 | H10: =F10*G10
B11: C | C11: 0.117 | D11: 0.702 | E11: =D11*0.88 | F11: =D11-E11 | G11: 118000 | H11: =F11*G11
B12: O | C12: 0.71 | D12: 4.26 | E12: =D12*0.88 | F12: =D12-E12 | G12: 5300 | H12: =F12*G12
B14: Annual safety benefit | H14: =SUM(H8:H12)
B15: PWF(0.07, 20) | H15: 10.594
B16: Present-value safety benefit | H16: =H14*H15

Sheet Optimization
B2: Optimization (MILP)
B5: Mathematical Formulation | N5: Site | O5: Alt | P5: Description | Q5: Cost | R5: Total benefit | S5: Net benefit | T5: Fund? (0/1)
B6: Decision variables | N6: 1 | O6: 0 | P6: Do nothing | Q6: =Inputs!G11 | R6: =Inputs!J11 | S6: =Inputs!K11 | T6: 0
B7: x_ij ∈ {0, 1} for each alternative j at site i (range T6:T7, yellow cells) | N7: 1 | O7: 1 | P7: Lane widening 10ft → 12ft (CMF 0.88) | Q7: =Inputs!G12 | R7: =Inputs!J12 | S7: =Inputs!K12 | T7: 0
B9: Objective
B10: Maximize: Z = Σ_i Σ_j NetBenefit_ij × x_ij | N10: Aggregates
B11: (computed at cell Q13) | N11: Total cost | Q11: =SUMPRODUCT(Q6:Q7,T6:T7)
N12: Total benefit | Q12: =SUMPRODUCT(R6:R7,T6:T7)
B13: Subject to | N13: Net benefit (objective) | Q13: =SUMPRODUCT(S6:S7,T6:T7)
B14: Budget: Σ_i Σ_j Cost_ij × x_ij ≤ Budget
B15: (computed at Q11, ≤ $1,000,000)
B16: Mutex: Σ_j x_ij ≤ 1 for each site i | N16: Pick at most one alternative per site
B17: (constraint cells, O18:O18) | N17: Site | O17: Sum of decisions | P17: Limit
B18: Binary: x_ij ∈ {0, 1} | N18: 1 | O18: =SUM(T6,T7) | P18: 1
B20: Solver Setup
B21: Top of Solver dialog
B22: Field | C22: Value
B23: Set Objective | C23: $Q$13
B24: To | C24: Max (radio button)
B25: By Changing Cells | C25: $T$6:$T$7
B26: Solving Method | C26: Simplex LP
B29: Constraints (click 'Add' for each row)
B30: Cell Reference | C30: Op | D30: Constraint
B31: $T$6:$T$7 | C31: bin | D31: —
B32: $Q$11 | C32: <= | D32: 1000000
B33: $O$18 | C33: <= | D33: 1
B35: Bottom of dialog
B36: Make Unconstrained Vars Non-Negative | C36: checked (default)
B37: Solving Method | C37: Simplex LP

Sheet Results
B2: Results
B4: Summary
B5: Match indicator | C5: =IF(SUM(Optimization!T6:T7)=0,"Run Solver",IF(ROUND(Optimization!Q13,0)=ROUND(D5,0),"PASS","FAIL")) | D5: 1493914
B7: Quantity | C7: Solver result | D7: Expected
B8: Total cost | C8: =Optimization!Q11 | D8: 750000
B9: Total net benefit | C9: =Optimization!Q13 | D9: 1493914
B11: Selected alternatives
B12: Site | C12: Alt | D12: Description
B13: 1 | C13: =Optimization!T6*Optimization!O6+Optimization!T7*Optimization!O7 | D13: =IF(Optimization!T6=1,Optimization!P6,IF(Optimization!T7=1,Optimization!P7,"(none selected)"))
